qbreader/__init__.py
qbreader/_api_utils.py
qbreader/_consts.py
qbreader/asynchronous.py
qbreader/py.typed
qbreader/synchronous.py
qbreader/types.py
qbreader-1.0.1.dist-info/LICENSE
qbreader-1.0.1.dist-info/METADATA
qbreader-1.0.1.dist-info/WHEEL
qbreader-1.0.1.dist-info/RECORD
