Metadata-Version: 2.3
Name: qbreader
Version: 1.0.1
Summary: Quizbowl library and Python wrapper for the qbreader API
License: MIT
Keywords: quizbowl,quiz bowl,qbreader
Author: Sky "skysomorphic" Hong
Author-email: skysomorphic@pm.me
Maintainer: Sky "skysomorphic" Hong
Maintainer-email: skysomorphic@pm.me
Requires-Python: >=3.11
Classifier: Development Status :: 5 - Production/Stable
Classifier: Intended Audience :: Developers
Classifier: Intended Audience :: Education
Classifier: Intended Audience :: Science/Research
Classifier: License :: OSI Approved :: MIT License
Classifier: Operating System :: OS Independent
Classifier: Programming Language :: Python :: 3
Classifier: Programming Language :: Python :: 3.11
Classifier: Programming Language :: Python :: 3.12
Classifier: Programming Language :: Python :: 3.13
Classifier: Topic :: Games/Entertainment
Classifier: Topic :: Software Development :: Libraries :: Python Modules
Classifier: Typing :: Typed
Requires-Dist: aiohttp (>=3.8.4,<4.0.0)
Requires-Dist: requests (>=2.31.0,<3.0.0)
Project-URL: Documentation, https://python-qbreader.readthedocs.io/
Project-URL: Homepage, https://github.com/qbreader/python-module
Project-URL: Repository, https://github.com/qbreader/python-module
